{
  "dashboard": {
    "title": "WAOOAW System Overview",
    "tags": ["waooaw", "overview"],
    "timezone": "browser",
    "schemaVersion": 16,
    "version": 1,
    "refresh": "30s",
    "panels": [
      {
        "id": 1,
        "type": "stat",
        "title": "Services Up",
        "gridPos": {"h": 4, "w": 6, "x": 0, "y": 0},
        "targets": [
          {
            "expr": "sum(up)",
            "refId": "A"
          }
        ]
      },
      {
        "id": 2,
        "type": "stat",
        "title": "Total Requests/s",
        "gridPos": {"h": 4, "w": 6, "x": 6, "y": 0},
        "targets": [
          {
            "expr": "sum(rate(http_requests_total[5m]))",
            "refId": "A"
          }
        ]
      },
      {
        "id": 3,
        "type": "stat",
        "title": "Error Rate",
        "gridPos": {"h": 4, "w": 6, "x": 12, "y": 0},
        "targets": [
          {
            "expr": "sum(rate(http_requests_total{status=~\"5..\"}[5m])) / sum(rate(http_requests_total[5m]))",
            "refId": "A"
          }
        ],
        "fieldConfig": {
          "defaults": {
            "unit": "percentunit",
            "thresholds": {
              "mode": "absolute",
              "steps": [
                {"value": 0, "color": "green"},
                {"value": 0.01, "color": "yellow"},
                {"value": 0.05, "color": "red"}
              ]
            }
          }
        }
      },
      {
        "id": 4,
        "type": "stat",
        "title": "P95 Response Time",
        "gridPos": {"h": 4, "w": 6, "x": 18, "y": 0},
        "targets": [
          {
            "expr": "histogram_quantile(0.95, rate(http_request_duration_seconds_bucket[5m]))",
            "refId": "A"
          }
        ],
        "fieldConfig": {
          "defaults": {
            "unit": "s"
          }
        }
      },
      {
        "id": 5,
        "type": "graph",
        "title": "Request Rate by Service",
        "gridPos": {"h": 8, "w": 12, "x": 0, "y": 4},
        "targets": [
          {
            "expr": "sum(rate(http_requests_total[5m])) by (service)",
            "legendFormat": "{{service}}",
            "refId": "A"
          }
        ]
      },
      {
        "id": 6,
        "type": "graph",
        "title": "Response Time by Service",
        "gridPos": {"h": 8, "w": 12, "x": 12, "y": 4},
        "targets": [
          {
            "expr": "histogram_quantile(0.95, rate(http_request_duration_seconds_bucket[5m])) by (service)",
            "legendFormat": "{{service}} P95",
            "refId": "A"
          }
        ]
      }
    ]
  }
}
